MANIFEST.in
requirements.txt
setup.py
pyFootyApi/Country.py
pyFootyApi/PyFootyApi.py
pyFootyApi/Season.py
pyFootyApi/TeamPlayer.py
pyFootyApi/__init__.py
pyFootyApi/__main__.py
pyFootyApi/helper/Cache.py
pyFootyApi/helper/IObject.py
pyFootyApi/helper/__init__.py
pyfootball_api.egg-info/PKG-INFO
pyfootball_api.egg-info/SOURCES.txt
pyfootball_api.egg-info/dependency_links.txt
pyfootball_api.egg-info/entry_points.txt
pyfootball_api.egg-info/requires.txt
pyfootball_api.egg-info/top_level.txt