Metadata-Version: 2.1
Name: pyfootball-api
Version: 0.2.0
Summary: A wrapper for https://www.api-football.com/
Home-page: UNKNOWN
Author: Marco Müllner
Author-email: muellnermarco@gmail.com
License: UNKNOWN
Platform: UNKNOWN
Classifier: Programming Language :: Python :: 3.6
Classifier: Programming Language :: Python :: 3.7
Classifier: Programming Language :: Python :: 3.8
Classifier: License :: OSI Approved :: MIT License
Classifier: Operating System :: OS Independent
